taskclient/__init__.py
taskclient/connection.py
taskclient/core.py
taskclient/drivers.py
taskclient/exceptions.py
task_client-1.0.1.dist-info/LICENSE
task_client-1.0.1.dist-info/METADATA
task_client-1.0.1.dist-info/WHEEL
task_client-1.0.1.dist-info/entry_points.txt
task_client-1.0.1.dist-info/top_level.txt
task_client-1.0.1.dist-info/RECORD
